upendra/__init__.py
upendra/cli.py
upendra-0.1.0.dist-info/METADATA
upendra-0.1.0.dist-info/WHEEL
upendra-0.1.0.dist-info/entry_points.txt
upendra-0.1.0.dist-info/RECORD
