Metadata-Version: 2.4
Name: upendra
Version: 0.1.0
Summary: Add your description here
Author-email: Upendra Panda <upendra.panda@intel.com>
Requires-Python: >=3.13.5
Requires-Dist: panda>=0.3.1
Requires-Dist: rich>=14.2.0
Requires-Dist: transformers>=4.57.0
Requires-Dist: typer>=0.19.2
